docs/README.md
docs/conf.py
private-gpt/private_gpt/__init__.py
private-gpt/private_gpt/__main__.py
private-gpt/private_gpt/constants.py
private-gpt/private_gpt/di.py
private-gpt/private_gpt/launcher.py
private-gpt/private_gpt/main.py
private-gpt/private_gpt/paths.py
private-gpt/private_gpt/components/__init__.py
private-gpt/private_gpt/components/embedding/__init__.py
private-gpt/private_gpt/components/embedding/embedding_component.py
private-gpt/private_gpt/components/embedding/custom/__init__.py
private-gpt/private_gpt/components/embedding/custom/sagemaker.py
private-gpt/private_gpt/components/ingest/__init__.py
private-gpt/private_gpt/components/ingest/ingest_component.py
private-gpt/private_gpt/components/ingest/ingest_helper.py
private-gpt/private_gpt/components/llm/__init__.py
private-gpt/private_gpt/components/llm/llm_component.py
private-gpt/private_gpt/components/llm/prompt_helper.py
private-gpt/private_gpt/components/llm/custom/__init__.py
private-gpt/private_gpt/components/llm/custom/sagemaker.py
private-gpt/private_gpt/components/node_store/__init__.py
private-gpt/private_gpt/components/node_store/node_store_component.py
private-gpt/private_gpt/components/vector_store/__init__.py
private-gpt/private_gpt/components/vector_store/batched_chroma.py
private-gpt/private_gpt/components/vector_store/vector_store_component.py
private-gpt/private_gpt/open_ai/__init__.py
private-gpt/private_gpt/open_ai/openai_models.py
private-gpt/private_gpt/open_ai/extensions/__init__.py
private-gpt/private_gpt/open_ai/extensions/context_filter.py
private-gpt/private_gpt/server/__init__.py
private-gpt/private_gpt/server/chat/__init__.py
private-gpt/private_gpt/server/chat/chat_router.py
private-gpt/private_gpt/server/chat/chat_service.py
private-gpt/private_gpt/server/chunks/__init__.py
private-gpt/private_gpt/server/chunks/chunks_router.py
private-gpt/private_gpt/server/chunks/chunks_service.py
private-gpt/private_gpt/server/completions/__init__.py
sphinxcontrib_osint-0.5.0.dist-info/licenses/LICENSE
sphinxcontrib_osint-0.5.0.dist-info/METADATA
sphinxcontrib_osint-0.5.0.dist-info/WHEEL
sphinxcontrib_osint-0.5.0.dist-info/entry_points.txt
sphinxcontrib_osint-0.5.0.dist-info/top_level.txt
sphinxcontrib_osint-0.5.0.dist-info/RECORD
