Metadata-Version: 2.4
Name: sphinxcontrib-osint
Version: 0.5.0
Summary: Manage, archive and analyze your data collected during your OSInt quest and generate a report with sphinx.
Author-email: bibi21000 <bibi21000@gmail.com>
Maintainer-email: bibi21000 <bibi21000@gmail.com>
License-Expression: MIT AND (Apache-2.0 OR BSD-2-Clause)
Project-URL: HomePage, https://github.com/bibi21000/sphinxcontrib-osint
Project-URL: Issues, https://github.com/bibi21000/sphinxcontrib-osint/issues
Project-URL: Changelog, https://github.com/bibi21000/sphinxcontrib-osint/blob/master/CHANGELOG.md
Project-URL: Documentation, https://bibi21000.github.io/sphinxcontrib-osint/
Classifier: Development Status :: 4 - Beta
Classifier: Intended Audience :: Developers
Classifier: Topic :: Internet
Classifier: Topic :: Office/Business
Classifier: Topic :: Text Processing
Classifier: Programming Language :: Python
Classifier: Programming Language :: Python :: 3
Classifier: Programming Language :: Python :: 3.9
Classifier: Programming Language :: Python :: 3.10
Classifier: Programming Language :: Python :: 3.11
Classifier: Programming Language :: Python :: 3.12
Classifier: Programming Language :: Python :: 3.13
Classifier: Programming Language :: Python :: 3.14
Classifier: Operating System :: OS Independent
Requires-Python: >=3.9
License-File: LICENSE
Requires-Dist: sphinx
Requires-Dist: tldextract
Requires-Dist: sphinx-toolbox
Requires-Dist: click
Requires-Dist: python-dateutil
Provides-Extra: pdf
Requires-Dist: pdfkit; extra == "pdf"
Provides-Extra: text
Requires-Dist: trafilatura; extra == "text"
Requires-Dist: lxml_html_clean; extra == "text"
Requires-Dist: translators; extra == "text"
Requires-Dist: langdetect; extra == "text"
Requires-Dist: pytubefix; extra == "text"
Requires-Dist: PyMuPDF; extra == "text"
Provides-Extra: youtube
Requires-Dist: translators; extra == "youtube"
Requires-Dist: langdetect; extra == "youtube"
Requires-Dist: pytubefix; extra == "youtube"
Provides-Extra: analyse
Requires-Dist: nltk; extra == "analyse"
Requires-Dist: textblob; extra == "analyse"
Requires-Dist: spacy; extra == "analyse"
Requires-Dist: wordcloud; extra == "analyse"
Requires-Dist: python-iso639; extra == "analyse"
Requires-Dist: matplotlib; extra == "analyse"
Requires-Dist: pyfonts; extra == "analyse"
Provides-Extra: whois
Requires-Dist: python-whois; extra == "whois"
Provides-Extra: ai
Requires-Dist: transformers; extra == "ai"
Requires-Dist: torch; extra == "ai"
Requires-Dist: pyspellchecker; extra == "ai"
Requires-Dist: language-tool-python; extra == "ai"
Requires-Dist: textblob; extra == "ai"
Requires-Dist: hunspell; extra == "ai"
Requires-Dist: rouge; extra == "ai"
Requires-Dist: nltk; extra == "ai"
Provides-Extra: bsky
Requires-Dist: atproto; extra == "bsky"
Requires-Dist: requests; extra == "bsky"
Requires-Dist: matplotlib; extra == "bsky"
Requires-Dist: numpy; extra == "bsky"
Requires-Dist: textparser; extra == "bsky"
Requires-Dist: pillow; extra == "bsky"
Requires-Dist: language-tool-python; extra == "bsky"
Requires-Dist: langdetect; extra == "bsky"
Requires-Dist: translators; extra == "bsky"
Requires-Dist: gdshortener; extra == "bsky"
Provides-Extra: dev
Requires-Dist: pytest; extra == "dev"
Requires-Dist: coverage[toml]; extra == "dev"
Requires-Dist: pytest-cov; extra == "dev"
Requires-Dist: pytest-mock; extra == "dev"
Requires-Dist: pytest-random-order; extra == "dev"
Requires-Dist: ruff; extra == "dev"
Provides-Extra: doc
Requires-Dist: sphinx-exec-code; extra == "doc"
Requires-Dist: pydata-sphinx-theme; extra == "doc"
Requires-Dist: myst-parser; extra == "doc"
Requires-Dist: sphinx-prompt; extra == "doc"
Requires-Dist: sphinxcontrib-programoutput; extra == "doc"
Provides-Extra: build
Requires-Dist: build; extra == "build"
Requires-Dist: twine; extra == "build"
Provides-Extra: carto
Requires-Dist: cartopy; extra == "carto"
Requires-Dist: geopy; extra == "carto"
Requires-Dist: pycountry; extra == "carto"
Requires-Dist: matplotlib; extra == "carto"
Provides-Extra: timeline
Requires-Dist: matplotlib; extra == "timeline"
Provides-Extra: app
Requires-Dist: flask; extra == "app"
Requires-Dist: Flask-Babel; extra == "app"
Dynamic: license-file
